mufzk/__init__.py
mufzk/_version.py
mufzk/comp2083.py
mufzk/graph.py
mufzk/oracles.py
mufzk/quantum.py
mufzk/vector.py
mufzk/quantum/__init__.py
mufzk/quantum/circuit_analyzer.py
mufzk/quantum/oracles.py
mufzk/quantum/quantum.py
mufzk/quantum/utils.py
mufzk-0.5.0.dist-info/METADATA
mufzk-0.5.0.dist-info/WHEEL
mufzk-0.5.0.dist-info/top_level.txt
mufzk-0.5.0.dist-info/RECORD
