Metadata-Version: 2.1
Name: mufzk
Version: 0.5.0
Requires-Dist: numpy<=2.0
Requires-Dist: scipy>=1.13.1
Requires-Dist: Faker>=37.1.0
Requires-Dist: networkx>=3.4
Requires-Dist: matplotlib>=3.10
